odoo10_addon_product_service_duration-10.0.1.0.0-py2.7-nspkg.pth
odoo/addons/product_service_duration/README.rst
odoo/addons/product_service_duration/__init__.py
odoo/addons/product_service_duration/__manifest__.py
odoo/addons/product_service_duration/demo/calendar_event_demo.xml
odoo/addons/product_service_duration/demo/product_product_demo.xml
odoo/addons/product_service_duration/models/__init__.py
odoo/addons/product_service_duration/models/calendar_event.py
odoo/addons/product_service_duration/models/product_product.py
odoo/addons/product_service_duration/static/description/icon.png
odoo/addons/product_service_duration/tests/__init__.py
odoo/addons/product_service_duration/tests/test_calendar_event.py
odoo/addons/product_service_duration/tests/test_product_product.py
odoo/addons/product_service_duration/views/calendar_event_view.xml
odoo/addons/product_service_duration/views/product_product_view.xml
odoo10_addon_product_service_duration-10.0.1.0.0.dist-info/DESCRIPTION.rst
odoo10_addon_product_service_duration-10.0.1.0.0.dist-info/METADATA
odoo10_addon_product_service_duration-10.0.1.0.0.dist-info/RECORD
odoo10_addon_product_service_duration-10.0.1.0.0.dist-info/WHEEL
odoo10_addon_product_service_duration-10.0.1.0.0.dist-info/metadata.json
odoo10_addon_product_service_duration-10.0.1.0.0.dist-info/namespace_packages.txt
odoo10_addon_product_service_duration-10.0.1.0.0.dist-info/top_level.txt
